Metadata-Version: 2.4
Name: nenupy
Version: 2.8.5
Summary: NenuFAR Python package
Author-email: Alan Loh <alan.loh@obspm.fr>
Project-URL: homepage, https://github.com/AlanLoh/nenupy
Project-URL: documentation, https://nenupy.readthedocs.io
Project-URL: repository, https://github.com/AlanLoh/nenupy
Classifier: Programming Language :: Python :: 3
Classifier: Intended Audience :: Science/Research
Requires-Python: >=3.8
License-File: LICENSE
Requires-Dist: astropy
Requires-Dist: reproject
Requires-Dist: pyproj
Requires-Dist: dask[array]
Requires-Dist: healpy
Requires-Dist: pytz
Requires-Dist: h5py
Provides-Extra: mocpy
Requires-Dist: mocpy; extra == "mocpy"
Dynamic: license-file
